[{"_path":"/tags/databases/oracle","_dir":"databases","_draft":false,"_partial":false,"_locale":"","title":"Oracle","description":"Oracle 是全球最大的信息管理软件及服务供应商，总部位于美国加州 Redwood Shore。Oracle 公司（甲骨文）自 1977 年成立以来，始终致力于提供卓越的数据库解决方案和软件服务。Oracle 开发的关系数据库产品性能卓越，被广泛采用于财富排行榜上的前 1000 家公司以及众多大型网站，是世界最好的数据库产品之一。","name":"oracle","icon":"simple-icons:oracle","_type":"markdown","_id":"content:tags:databases:oracle.md","_source":"content","_file":"tags/databases/oracle.md","_extension":"md"},{"_path":"/tags/databases/redis","_dir":"databases","_draft":false,"_partial":false,"_locale":"","title":"Redis","description":"Redis 是一个功能强大、性能优越的Key-Value数据库，能够满足各种复杂的业务需求，提高系统的整体性能和稳定性。如需更多信息，建议查阅Redis的官方文档或相关教程。","name":"redis","icon":"logos:redis","_type":"markdown","_id":"content:tags:databases:redis.md","_source":"content","_file":"tags/databases/redis.md","_extension":"md"}]