[{"_path":"/docs/guide","_dir":"docs","_draft":false,"_partial":false,"_locale":"","title":"VVLL.NET 部署指南","description":"","tags":"github","_type":"markdown","_id":"content:docs:guide.md","_source":"content","_file":"docs/guide.md","_extension":"md"},{"_path":"/notes/css/css-protips","_dir":"css","_draft":false,"_partial":false,"_locale":"","title":"CSS 专业技巧","description":"一个帮你提升 CSS 技巧的收藏集。","icon":"noto-v1:light-bulb","tags":"css","author":"iczp","date":"2024-06-27T00:00:00.000Z","_type":"markdown","_id":"content:notes:css:css-protips.md","_source":"content","_file":"notes/css/css-protips.md","_extension":"md"}]