[{"_path":"/projects/chatmaxim-flutter","_dir":"projects","_draft":false,"_partial":false,"_locale":"","title":"ChatMaxim 移动端(Flutter)","description":"VVLL.net（Vite Vue Link Lab）是一个网站，主要提供关于Vite、Vue和相关开发文档的资源和信息。以下是该网站的主要内容和特点：","layout":"article","tags":"vue tailwindcss css","_type":"markdown","_id":"content:projects:chatmaxim-flutter.md","_source":"content","_file":"projects/chatmaxim-flutter.md","_extension":"md"},{"_path":"/sub/guide","_dir":"sub","_draft":false,"_partial":false,"_locale":"","title":"sub Guide.md","description":"Back to Home","layout":"article","tags":"vue tailwindcss css","_type":"markdown","_id":"content:sub:guide.md","_source":"content","_file":"sub/guide.md","_extension":"md"}]