{"_path":"/sub/guide","_dir":"sub","_draft":false,"_partial":false,"_locale":"","title":"sub Guide.md","description":"Back to Home","layout":"article","tags":"vue tailwindcss css","body":{"type":"root","children":[{"type":"element","tag":"h1","props":{"id":"sub-guidemd"},"children":[{"type":"text","value":"sub Guide.md"}]},{"type":"element","tag":"p","props":{},"children":[{"type":"element","tag":"a","props":{"href":"../"},"children":[{"type":"text","value":"Back to Home"}]}]}],"toc":{"title":"","searchDepth":5,"depth":5,"links":[]}},"_type":"markdown","_id":"content:sub:guide.md","_source":"content","_file":"sub/guide.md","_extension":"md"}