[{"_path":"/notes/ts/object/guide","_dir":"object","_draft":false,"_partial":false,"_locale":"","title":"总览","description":"在 TypeScript 中，Object 是 JavaScript 中的基本对象类型，包含多种方法来操作和处理对象。","tags":"ts","author":"iczp","date":"2024-06-20T00:00:00.000Z","_type":"markdown","_id":"content:notes:ts:object:0.guide.md","_source":"content","_file":"notes/ts/object/0.guide.md","_extension":"md"},{"_path":"/notes/ts/object/create","_dir":"object","_draft":false,"_partial":false,"_locale":"","title":"Object.create","description":"用于创建一个新对象，并将其原型设置为指定的对象。","tags":"ts","author":"iczp","date":"2024-06-20T00:00:00.000Z","_type":"markdown","_id":"content:notes:ts:object:create.md","_source":"content","_file":"notes/ts/object/create.md","_extension":"md"}]